{
	"visual": {
        "costBudgetCompareList": [957467487.9,1059017069.95,1131552485.7,1247609150.9,1311440316.76,1415891315.44,1468116814.78,1497130981.08,1531947980.64,1581272063.35,1630596146.06,1740849978],
        "incomeBudgetCompareList": [15673794816.9,17336166994.45,18523575692.7,20423429609.9,21468349264.36,23178217789.84,24033152052.58,24508115531.88,25078071707.04,25885509621.85,26692947536.66,28497808758],
        "line_xAxis_data": ["1月","2月","3月","4月","5月","6月","7月","8月","9月","10月","11月","12月"],
        "business_income_list": [17163299857.9,19011512278.45,20319343049.7,22350798865.9,23492308162.36,25377806790.84,26257778984.58,26770746976.88,27409452772.04,28287741799.85,29202071699.66,31163848764],
        "compositionDatas": [
            {
                "bar2List": [{"name": "委托加工成本","value": 5119505041},{"name": "商品销售成本","value": 2776972528.9},{"name": "技术开发成本","value": 2149505041}],
                "bar1List": [{"name": "委托加工收入","value": 7301235539.2},{"name": "商品销售收入","value": 3963299857.9},{"name": "技术开发收入","value": 8419505041}],
                "bar1Title": "2017年1月收入组成",
                "bar2Title": "2017年1月成本组成",
                "id": 1
            },
            {
                "bar2List": [{"name": "委托加工成本","value": 5690345284},{"name": "商品销售成本","value": 3099362353.95},{"name": "技术开发成本","value": 2405345284}],
                "bar1List": [{"name": "委托加工收入","value": 8103471441.1},{"name": "商品销售收入","value": 4411512278.45},{"name": "技术开发收入","value": 9340345284}],
                "bar1Title": "2017年2月收入组成",
                "bar2Title": "2017年2月成本组成",
                "id": 2
            },
            {
                "bar2List": [{"name": "委托加工成本","value": 6085767357},{"name": "商品销售成本","value": 3317319842.7},{"name": "技术开发成本","value": 2575767357}],
                "bar1List": [{"name": "委托加工收入","value": 8664176127.6},{"name": "商品销售收入","value": 4719343049.7},{"name": "技术开发收入","value": 9985767357}],
                "bar1Title": "2017年3月收入组成",
                "bar2Title": "2017年3月成本组成",
                "id": 3
            },
            {
                "bar2List": [{"name": "委托加工成本","value": 6657369256},{"name": "商品销售成本","value": 3604978406.9},{"name": "技术开发成本","value": 2787369256}],
                "bar1List": [{"name": "委托加工收入","value": 9500230208.2},{"name": "商品销售收入","value": 5150798865.9},{"name": "技术开发收入","value": 10957369256}],
                "bar1Title": "2017年4月收入组成",
                "bar2Title": "2017年4月成本组成",
                "id": 4
            },
            {
                "bar2List": [{"name": "委托加工成本","value": 6995958898},{"name": "商品销售成本","value": 3787399214.76},{"name": "技术开发成本","value": 2927958898}],
                "bar1List": [{"name": "委托加工收入","value": 9984268550.08},{"name": "商品销售收入","value": 5412308162.36},{"name": "技术开发收入","value": 11515958898}],
                "bar1Title": "2017年5月收入组成",
                "bar2Title": "2017年5月成本组成",
                "id": 5
            },
            {
                "bar2List": [{"name": "委托加工成本","value": 7567589001},{"name": "商品销售成本","value": 4103480316.44},{"name": "技术开发成本","value": 3175589001}],
                "bar1List": [{"name": "委托加工收入","value": 10793905616.52},{"name": "商品销售收入","value": 5857806790.84},{"name": "技术开发收入","value": 12447589001}],
                "bar1Title": "2017年6月收入组成",
                "bar2Title": "2017年6月成本组成",
                "id": 6
            },
            {
                "bar2List": [{"name": "委托加工成本","value": 7790626932},{"name": "商品销售成本","value": 4198743746.78},{"name": "技术开发成本","value": 3236626932}],
                "bar1List": [{"name": "委托加工收入","value": 11135947029.24},{"name": "商品销售收入","value": 6017778984.58},{"name": "技术开发收入","value": 12850626932}],
                "bar1Title": "2017年7月收入组成",
                "bar2Title": "2017年7月成本组成",
                "id": 7
            },
            {
                "bar2List": [{"name": "委托加工成本","value": 7938631445},{"name": "商品销售成本","value": 4275762426.08},{"name": "技术开发成本","value": 3294631445}],
                "bar1List": [{"name": "委托加工收入","value": 11350064587.64},{"name": "商品销售收入","value": 6130746976.88},{"name": "技术开发收入","value": 13098631445}],
                "bar1Title": "2017年8月收入组成",
                "bar2Title": "2017年8月成本组成",
                "id": 8
            },
            {
                "bar2List": [{"name": "委托加工成本","value": 8139381065},{"name": "商品销售成本","value": 4391329045.64},{"name": "技术开发成本","value": 3387381065}],
                "bar1List": [{"name": "委托加工收入","value": 11630149862.12},{"name": "商品销售收入","value": 6289452772.04},{"name": "技术开发收入","value": 13419381065}],
                "bar1Title": "2017年9月收入组成",
                "bar2Title": "2017年9月成本组成",
                "id": 9
            },
            {
                "bar2List": [{"name": "委托加工成本","value": 8397232178},{"name": "商品销售成本","value": 4528504241.35},{"name": "技术开发成本","value": 3492232178}],
                "bar1List": [{"name": "委托加工收入","value": 12000393152.3},{"name": "商品销售收入","value": 6487741799.85},{"name": "技术开发收入","value": 13847232178}],
                "bar1Title": "2017年10月收入组成",
                "bar2Title": "2017年10月成本组成",
                "id": 10
            },
            {
                "bar2List": [{"name": "委托加工成本","value": 8691124163},{"name": "商品销售成本","value": 4701720309.06},{"name": "技术开发成本","value": 3633124163}],
                "bar1List": [{"name": "委托加工收入","value": 12406677314.48},{"name": "商品销售收入","value": 6722071699.66},{"name": "技术开发收入","value": 14311124163}],
                "bar1Title": "2017年11月收入组成",
                "bar2Title": "2017年11月成本组成",
                "id": 11
            },
            {
                "bar2List": [{"name": "委托加工成本","value": 9266040006},{"name": "商品销售成本","value": 5006889984},{"name": "技术开发成本","value": 3866040006}],
                "bar1List": [{"name": "委托加工收入","value": 13232822730},{"name": "商品销售收入","value": 7163848764},{"name": "技术开发收入","value": 15266040006}],
                "bar1Title": "2017年12月收入组成",
                "bar2Title": "2017年12月成本组成",
                "id": 12
            }
        ],
        "operating_cost_list": [6076972528.9,6749362353.95,7217319842.7,7904978406.9,8307399214.76,8983480316.44,9258743746.78,9435762426.08,9671329045.64,9978504241.35,10321720309.06,11006889984]
    }
}